sqlconsole/__init__.py
sqlconsole/admin.py
sqlconsole/apps.py
sqlconsole/download.py
sqlconsole/forms.py
sqlconsole/models.py
sqlconsole/views.py
sqlconsole/migrations/0001_initial.py
sqlconsole/migrations/0002_rename_created_querylog_created_at_and_more.py
sqlconsole/migrations/__init__.py
sqlconsole/static/sqlconsole/css/sqlconsole.css
sqlconsole/templates/admin/sqlconsole.djhtml
sqlconsole/templates/admin/sqlconsole/change_list_object_tools.html
django_sqlconsole-1.4.0.dist-info/LICENSE
django_sqlconsole-1.4.0.dist-info/METADATA
django_sqlconsole-1.4.0.dist-info/WHEEL
django_sqlconsole-1.4.0.dist-info/top_level.txt
django_sqlconsole-1.4.0.dist-info/RECORD
